allmydata/__init__.py
allmydata/__main__.py
allmydata/_monkeypatch.py
allmydata/_version.py
allmydata/blacklist.py
allmydata/check_results.py
allmydata/client.py
allmydata/codec.py
allmydata/deep_stats.py
allmydata/dirnode.py
allmydata/grid_manager.py
allmydata/hashtree.py
allmydata/history.py
allmydata/interfaces.py
allmydata/listeners.py
allmydata/monitor.py
allmydata/node.py
allmydata/nodemaker.py
allmydata/protocol_switch.py
allmydata/stats.py
allmydata/storage_client.py
allmydata/unknown.py
allmydata/uri.py
allmydata/webish.py
allmydata/cli/__init__.py
allmydata/cli/grid_manager.py
allmydata/crypto/__init__.py
allmydata/crypto/aes.py
allmydata/crypto/ed25519.py
allmydata/crypto/error.py
allmydata/crypto/rsa.py
allmydata/crypto/util.py
allmydata/frontends/__init__.py
allmydata/frontends/auth.py
allmydata/frontends/sftpd.py
allmydata/immutable/__init__.py
allmydata/immutable/checker.py
allmydata/immutable/encode.py
allmydata/immutable/filenode.py
allmydata/immutable/happiness_upload.py
allmydata/immutable/layout.py
allmydata/immutable/literal.py
allmydata/immutable/offloaded.py
allmydata/immutable/repairer.py
allmydata/immutable/upload.py
allmydata/immutable/downloader/__init__.py
allmydata/immutable/downloader/common.py
allmydata/immutable/downloader/fetcher.py
allmydata/immutable/downloader/finder.py
allmydata/immutable/downloader/node.py
allmydata/immutable/downloader/segmentation.py
allmydata/immutable/downloader/share.py
allmydata/immutable/downloader/status.py
allmydata/introducer/__init__.py
allmydata/introducer/client.py
allmydata/introducer/common.py
allmydata/introducer/interfaces.py
allmydata/introducer/server.py
allmydata/mutable/__init__.py
allmydata/mutable/checker.py
allmydata/mutable/common.py
allmydata/mutable/filenode.py
allmydata/mutable/layout.py
allmydata/mutable/publish.py
allmydata/mutable/repairer.py
allmydata/mutable/retrieve.py
allmydata/mutable/servermap.py
allmydata/scripts/__init__.py
allmydata/scripts/admin.py
tahoe_lafs-1.20.0.dist-info/METADATA
tahoe_lafs-1.20.0.dist-info/WHEEL
tahoe_lafs-1.20.0.dist-info/entry_points.txt
tahoe_lafs-1.20.0.dist-info/licenses/COPYING.GPL
tahoe_lafs-1.20.0.dist-info/licenses/COPYING.TGPPL.rst
tahoe_lafs-1.20.0.dist-info/RECORD
