Metadata-Version: 2.4
Name: tahoe-lafs
Version: 1.20.0
Summary: secure, decentralized, fault-tolerant file store
Project-URL: Homepage, https://tahoe-lafs.org/
Project-URL: Documentation, https://tahoe-lafs.readthedocs.org/
Project-URL: Source code, https://github.com/tahoe-lafs/tahoe-lafs/
Author-email: the Tahoe-LAFS project <tahoe-dev@lists.tahoe-lafs.org>
License-Expression: GPL-2.0-or-later
License-File: COPYING.GPL
License-File: COPYING.TGPPL.rst
Classifier: Development Status :: 5 - Production/Stable
Classifier: Environment :: Console
Classifier: Environment :: Web Environment
Classifier: Intended Audience :: Developers
Classifier: Intended Audience :: End Users/Desktop
Classifier: Intended Audience :: System Administrators
Classifier: License :: DFSG approved
Classifier: License :: OSI Approved :: GNU General Public License (GPL)
Classifier: License :: Other/Proprietary License
Classifier: Natural Language :: English
Classifier: Operating System :: MacOS :: MacOS X
Classifier: Operating System :: Microsoft
Classifier: Operating System :: Microsoft :: Windows
Classifier: Operating System :: OS Independent
Classifier: Operating System :: POSIX
Classifier: Operating System :: POSIX :: Linux
Classifier: Operating System :: Unix
Classifier: Programming Language :: C
Classifier: Programming Language :: Python
Classifier: Programming Language :: Python :: 3
Classifier: Programming Language :: Python :: 3.9
Classifier: Programming Language :: Python :: 3.10
Classifier: Programming Language :: Python :: 3.11
Classifier: Programming Language :: Python :: 3.12
Classifier: Topic :: Software Development :: Libraries
Classifier: Topic :: System :: Archiving
Classifier: Topic :: System :: Archiving :: Backup
Classifier: Topic :: System :: Archiving :: Mirroring
Classifier: Topic :: System :: Distributed Computing
Classifier: Topic :: System :: Filesystems
Classifier: Topic :: System :: Systems Administration
Classifier: Topic :: Utilities
Requires-Python: >=3.9
Requires-Dist: attrs>=20.1.0
Requires-Dist: autobahn>=22.4.3
Requires-Dist: cbor2!=5.6.0
Requires-Dist: click>=8.1.1
Requires-Dist: collections-extended>=2.0.2
Requires-Dist: cryptography>=2.6
Requires-Dist: distro>=1.4.0
Requires-Dist: eliot>=1.14.0
Requires-Dist: filelock
Requires-Dist: foolscap>=21.7.0
Requires-Dist: foolscap>=23.3.0; python_version > '3.10'
Requires-Dist: future>=0.18.2
Requires-Dist: klein>=23.5.0
Requires-Dist: magic-wormhole>=0.10.2
Requires-Dist: netifaces
Requires-Dist: psutil
Requires-Dist: pycddl>=0.6.1
Requires-Dist: pyopenssl>=23.2.0
Requires-Dist: pyrsistent
Requires-Dist: pyutil>=3.3.0
Requires-Dist: pywin32!=226; sys_platform == 'win32'
Requires-Dist: pyyaml>=3.11
Requires-Dist: six>=1.10.0
Requires-Dist: treq
Requires-Dist: twisted[conch,tls]>=22.8.0
Requires-Dist: werkzeug!=2.2.0
Requires-Dist: zfec>=1.1.0
Requires-Dist: zope-interface>=3.6.0
Provides-Extra: build
Requires-Dist: dulwich; extra == 'build'
Requires-Dist: gpg; extra == 'build'
Requires-Dist: hatch-vcs; extra == 'build'
Requires-Dist: hatchling; extra == 'build'
Provides-Extra: i2p
Requires-Dist: txi2p-tahoe>=0.3.5; (python_version > '3.0') and extra == 'i2p'
Requires-Dist: txi2p; (python_version < '3.0') and extra == 'i2p'
Provides-Extra: test
Requires-Dist: beautifulsoup4; extra == 'test'
Requires-Dist: fixtures; extra == 'test'
Requires-Dist: html5lib; extra == 'test'
Requires-Dist: hypothesis>=3.6.1; extra == 'test'
Requires-Dist: mock; extra == 'test'
Requires-Dist: paramiko<2.9; extra == 'test'
Requires-Dist: prometheus-client==0.11.0; extra == 'test'
Requires-Dist: pytest; extra == 'test'
Requires-Dist: pytest-timeout; extra == 'test'
Requires-Dist: pytest-twisted; extra == 'test'
Requires-Dist: testtools; extra == 'test'
Requires-Dist: towncrier; extra == 'test'
Requires-Dist: tox; extra == 'test'
Requires-Dist: tox>=4.0.0; extra == 'test'
Requires-Dist: txi2p-tahoe>=0.3.5; (python_version > '3.0') and extra == 'test'
Requires-Dist: txi2p; (python_version < '3.0') and extra == 'test'
Requires-Dist: txtorcon>=23.5.0; extra == 'test'
Provides-Extra: testenv
Requires-Dist: coverage==7.2.5; extra == 'testenv'
Requires-Dist: junitxml==0.7; extra == 'testenv'
Requires-Dist: pip==23.3.1; extra == 'testenv'
Requires-Dist: python-subunit==1.4.2; extra == 'testenv'
Requires-Dist: subunitreporter==23.8.0; extra == 'testenv'
Requires-Dist: wheel==0.41.3; extra == 'testenv'
Provides-Extra: tor
Requires-Dist: txtorcon>=23.5.0; extra == 'tor'
